LICENSE
MANIFEST.in
README.rst
setup.py
test.py
doctpl/__init__.py
doctpl/core.py
doctpl/interface.py
doctpl.egg-info/PKG-INFO
doctpl.egg-info/SOURCES.txt
doctpl.egg-info/dependency_links.txt
doctpl.egg-info/entry_points.txt
doctpl.egg-info/requires.txt
doctpl.egg-info/top_level.txt