Metadata-Version: 1.1
Name: doctpl
Version: 0.1.2
Summary: CLI tool for quickly setting up templates for writing articles.
Home-page: https://github.com/haoxun/DocTemplate
Author: Zhan Haoxun
Author-email: programmer.zhx@gmail.com
License: MIT
Platform: UNKNOWN
Classifier: Development Status :: 3 - Alpha
Classifier: Programming Language :: Python
Classifier: Programming Language :: Python :: 3
Classifier: Operating System :: OS Independent
Classifier: License :: OSI Approved :: MIT License
